fmp_python/__init__.py
fmp_python/fmp.py
fmp_python/common/__init__.py
fmp_python/common/constants.py
fmp_python/common/fmpdecorator.py
fmp_python/common/fmpexception.py
fmp_python/common/fmpvalidator.py
fmp_python/common/requestbuilder.py
test_fmp_python/__init__.py
test_fmp_python/test_fmp.py
test_fmp_python/test_request_builder.py
fmp_python-0.1.4.dist-info/LICENSE
fmp_python-0.1.4.dist-info/METADATA
fmp_python-0.1.4.dist-info/WHEEL
fmp_python-0.1.4.dist-info/top_level.txt
fmp_python-0.1.4.dist-info/RECORD
